blargh/__init__.py
blargh/api/__init__.py
blargh/api/basic.py
blargh/api/flask/__init__.py
blargh/api/flask/api.py
blargh/api/flask/resource.py
blargh/data_model/__init__.py
blargh/data_model/data_model.py
blargh/data_model/object.py
blargh/data_model/fields/__init__.py
blargh/data_model/fields/field.py
blargh/data_model/fields/values.py
blargh/data_model/pg_schema_import/__init__.py
blargh/data_model/pg_schema_import/pg_schema_import.py
blargh/data_model/pg_schema_import/query.py
blargh/engine/__init__.py
blargh/engine/config.py
blargh/engine/engine.py
blargh/engine/instance.py
blargh/engine/world_cls.py
blargh/engine/storage/__init__.py
blargh/engine/storage/base_storage.py
blargh/engine/storage/dict.py
blargh/engine/storage/pickled_dict.py
blargh/engine/storage/pg/__init__.py
blargh/engine/storage/pg/pg_storage.py
blargh/engine/storage/pg/query.py
blargh/exceptions/__init__.py
blargh/exceptions/base.py
blargh/exceptions/client.py
blargh/exceptions/server.py
blargh-0.0.9.dist-info/LICENSE
blargh-0.0.9.dist-info/METADATA
blargh-0.0.9.dist-info/WHEEL
blargh-0.0.9.dist-info/top_level.txt
blargh-0.0.9.dist-info/RECORD
